README.md
setup.py
cachecontrol_uwsgi/__init__.py
cachecontrol_uwsgi.egg-info/PKG-INFO
cachecontrol_uwsgi.egg-info/SOURCES.txt
cachecontrol_uwsgi.egg-info/dependency_links.txt
cachecontrol_uwsgi.egg-info/requires.txt
cachecontrol_uwsgi.egg-info/top_level.txt