Metadata-Version: 2.1
Name: cachecontrol-uwsgi
Version: 1.0.0
Summary: A cache provider for CacheControl using UWSGI's caching framework.
Home-page: https://github.com/etene/cachecontrol-uwsgi
Author: etene
Author-email: etienne.noss+pypi@gmail.com
License: UNKNOWN
Platform: UNKNOWN
Classifier: Programming Language :: Python :: 2.7
Classifier: Programming Language :: Python :: 3.5
Classifier: Programming Language :: Python :: 3.6
Classifier: Programming Language :: Python :: 3.7
Classifier: Operating System :: OS Independent
